Metadata-Version: 1.1
Name: scene
Version: 0.0.1
Summary: Guessing movie genres from script snippets.
Home-page: https://github.com/yngtodd/scene
Author: Todd Young
Author-email: young.todd.mk@gmail.com
License: MIT
Keywords: scene
Platform: UNKNOWN
Classifier: Development Status :: 2 - Pre-Alpha
Classifier: Intended Audience :: Developers
Classifier: License :: OSI Approved :: MIT License
Classifier: Natural Language :: English
Classifier: Programming Language :: Python :: 3.6
Classifier: Programming Language :: Python :: Implementation :: PyPy
